<?xml version="1.0"?>
<!DOCTYPE hibernate-mapping PUBLIC "-//Hibernate/Hibernate Mapping DTD 3.0//EN"
"http://www.hibernate.org/dtd/hibernate-mapping-3.0.dtd">
<!-- Generated 21 May, 2016 5:04:23 PM by Hibernate Tools 4.3.1 -->
<hibernate-mapping>
    <class name="hibernate.OfficeHeld" table="office_held" catalog="bahamas" optimistic-lock="version">
        <composite-id name="id" class="hibernate.OfficeHeldId">
            <key-property name="contactId" type="int">
                <column name="CONTACT_ID" />
            </key-property>
            <key-property name="officeId" type="int">
                <column name="OFFICE_ID" />
            </key-property>
        </composite-id>
        <many-to-one name="contact" class="hibernate.Contact" update="false" insert="false" fetch="select">
            <column name="CONTACT_ID" not-null="true" />
        </many-to-one>
        <many-to-one name="officeList" class="hibernate.OfficeList" update="false" insert="false" fetch="select">
            <column name="OFFICE_ID" not-null="true" />
        </many-to-one>
        <property name="dateCreated" type="date">
            <column name="DATE_CREATED" length="10" not-null="true" />
        </property>
        <property name="createdBy" type="string">
            <column name="CREATED_BY" length="50" not-null="true" />
        </property>
        <property name="startOffice" type="date">
            <column name="START_OFFICE" length="10" not-null="true" />
        </property>
        <property name="endOffice" type="date">
            <column name="END_OFFICE" length="10" not-null="true" />
        </property>
        <property name="remarks" type="string">
            <column name="REMARKS" length="1000" />
        </property>
    </class>
</hibernate-mapping>
